hdmi_cec_to_adb/__init__.py
hdmi_cec_to_adb/bin/__init__.py
hdmi_cec_to_adb/bin/start_hdmi_cec_monitor.py
hdmi_cec_to_adb-0.2.dist-info/METADATA
hdmi_cec_to_adb-0.2.dist-info/WHEEL
hdmi_cec_to_adb-0.2.dist-info/entry_points.txt
hdmi_cec_to_adb-0.2.dist-info/top_level.txt
hdmi_cec_to_adb-0.2.dist-info/RECORD
