Metadata-Version: 2.1
Name: hdmi-cec-to-adb
Version: 0.2
Summary: hdmi_cec_to_adb
Home-page: https://github.com/paulsaccount/hdmi_cec_to_adb
Author: Paul Pavlish
Author-email: hello@paulpavlish.com
License: UNKNOWN
Platform: UNKNOWN
Requires-Dist: adb-shell
Requires-Dist: cec
